Metadata-Version: 1.0
Name: distrnd-probability
Version: 0.2
Summary: Gaussian and Binomial distributions
Home-page: UNKNOWN
Author: Varaprasad Gadi
Author-email: gvp3682@gmail.com
License: UNKNOWN
Platform: UNKNOWN
